pangea_azure_ai/__init__.py
pangea_azure_ai/errors.py
pangea_azure_ai/inference/__init__.py
pangea_azure_ai/inference/_client.py
pangea_azure_ai/py.typed
pangea_azure_ai-0.1.0.dist-info/WHEEL
pangea_azure_ai-0.1.0.dist-info/METADATA
pangea_azure_ai-0.1.0.dist-info/RECORD
