Metadata-Version: 2.4
Name: pangea-azure-ai
Version: 0.1.0
Summary: A wrapper around the Azure AI Inference SDK
Author: Pangea
Author-email: Pangea <support@pangea.cloud>
License-Expression: MIT
Requires-Dist: azure-ai-inference>=1.0.0b9
Requires-Dist: pangea-sdk>=6.6.0
Requires-Dist: typing-extensions>=4.15.0
Requires-Python: >=3.10
